setup.py
pysobus/__init__.py
pysobus/message_definitions.csv
pysobus/parser.py
pysobus.egg-info/PKG-INFO
pysobus.egg-info/SOURCES.txt
pysobus.egg-info/dependency_links.txt
pysobus.egg-info/requires.txt
pysobus.egg-info/top_level.txt