Metadata-Version: 1.1
Name: pysobus
Version: 0.0.3
Summary: Proprietary ISOBUS message specifications and decoding tools for yield data
Home-page: https://github.com/FarmLogs/pysobus
Author: Bryan Johnson
Author-email: bryan@farmlogs.com
License: UNKNOWN
Download-URL: https://github.com/FarmLogs/pysobus/tarball/0.0.3
Platform: UNKNOWN
